LICENSE
MANIFEST.in
README.rst
requirements.txt
setup.cfg
setup.py
demo/__init__.py
demo/manage.py
demo/settings.py
demo/urls.py
demo/wsgi.py
demo/demoapp/__init__.py
demo/demoapp/admin.py
demo/demoapp/apps.py
demo/demoapp/models.py
demo/demoapp/tests.py
demo/demoapp/views.py
demo/demoapp/migrations/0001_initial.py
demo/demoapp/migrations/0002_import_example_data.py
demo/demoapp/migrations/0003_auto_20190220_0430.py
demo/demoapp/migrations/__init__.py
django_reservation.egg-info/PKG-INFO
django_reservation.egg-info/SOURCES.txt
django_reservation.egg-info/dependency_links.txt
django_reservation.egg-info/not-zip-safe
django_reservation.egg-info/requires.txt
django_reservation.egg-info/top_level.txt
djreservation/__init__.py
djreservation/admin.py
djreservation/apps.py
djreservation/email.py
djreservation/forms.py
djreservation/middleware.py
djreservation/models.py
djreservation/product_manager.py
djreservation/register.py
djreservation/settings.py
djreservation/signals.py
djreservation/tests.py
djreservation/urls.py
djreservation/views.py
djreservation/__pycache__/__init__.cpython-39.pyc
djreservation/__pycache__/admin.cpython-39.pyc
djreservation/__pycache__/apps.cpython-39.pyc
djreservation/__pycache__/email.cpython-39.pyc
djreservation/__pycache__/forms.cpython-39.pyc
djreservation/__pycache__/middleware.cpython-39.pyc
djreservation/__pycache__/models.cpython-39.pyc
djreservation/__pycache__/product_manager.cpython-39.pyc
djreservation/__pycache__/settings.cpython-39.pyc
djreservation/__pycache__/signals.cpython-39.pyc
djreservation/__pycache__/urls.cpython-39.pyc
djreservation/__pycache__/views.cpython-39.pyc
djreservation/contrib/CRUD.py
djreservation/contrib/__init__.py
djreservation/locale/es/LC_MESSAGES/django.mo
djreservation/locale/es/LC_MESSAGES/django.po
djreservation/migrations/0001_initial.py
djreservation/migrations/0002_auto_20160903_0030.py
djreservation/migrations/0003_auto_20161004_1525.py
djreservation/migrations/0004_auto_20161005_0022.py
djreservation/migrations/0005_reservationtoken.py
djreservation/migrations/0006_reservationtoken_base_url.py
djreservation/migrations/0007_auto_20190220_0313.py
djreservation/migrations/__init__.py
