Metadata-Version: 2.1
Name: django-reservation
Version: 0.2.10
Summary: Powerful and dinamic reservation system in django.
Home-page: https://github.com/luisza/djreservation
Author: Luis Zarate
Author-email: luis.zarate@solvosoft.com
License: GNU General Public License v3 (GPLv3)
Platform: OS Independent
Classifier: Environment :: Web Environment
Classifier: Framework :: Django
Classifier: Framework :: Django :: 1.10
Classifier: Intended Audience :: Developers
Classifier: License :: OSI Approved :: GNU General Public License v3 (GPLv3)
Classifier: Operating System :: OS Independent
Classifier: Programming Language :: Python
Classifier: Programming Language :: Python :: 3.5
Classifier: Topic :: Internet :: WWW/HTTP
Classifier: Topic :: Internet :: WWW/HTTP :: Dynamic Content
Classifier: Topic :: Software Development :: Libraries :: Python Modules
Classifier: Development Status :: 4 - Beta
License-File: LICENSE
